junifer_eeg/__init__.py
junifer_eeg/__init__.pyi
junifer_eeg/_version.py
junifer_eeg/py.typed
junifer_eeg-0.0.0.dist-info/licenses/LICENSE
junifer_eeg-0.0.0.dist-info/METADATA
junifer_eeg-0.0.0.dist-info/WHEEL
junifer_eeg-0.0.0.dist-info/top_level.txt
junifer_eeg-0.0.0.dist-info/RECORD
