Metadata-Version: 2.4
Name: junifer_eeg
Version: 0.0.0
Summary: Junifer EEG extension
Author-email: Synchon Mandal <s.mandal@fz-juelich.de>, Fede Raimondo <f.raimondo@fz-juelich.de>
Maintainer-email: Synchon Mandal <s.mandal@fz-juelich.de>, Fede Raimondo <f.raimondo@fz-juelich.de>
License: AGPL-3.0-only
Project-URL: Source, https://github.com/juaml/junifer-eeg
Classifier: Development Status :: 4 - Beta
Classifier: Environment :: Console
Classifier: Intended Audience :: Developers
Classifier: Intended Audience :: Science/Research
Classifier: Intended Audience :: Education
Classifier: License :: OSI Approved
Classifier: Operating System :: OS Independent
Classifier: Programming Language :: Python :: 3
Classifier: Programming Language :: Python :: 3.10
Classifier: Programming Language :: Python :: 3.11
Classifier: Programming Language :: Python :: 3.12
Classifier: Programming Language :: Python :: 3.13
Classifier: Programming Language :: Python :: 3.14
Classifier: Topic :: Software Development
Classifier: Topic :: Scientific/Engineering
Classifier: Topic :: Utilities
Requires-Python: >=3.10
License-File: LICENSE
Requires-Dist: click<8.2,>=8.1.3
Requires-Dist: datalad<1.3.0,>=1.0.0
Requires-Dist: lazy_loader==0.4
Requires-Dist: structlog<26.0.0,>=25.0.0
Provides-Extra: dev
Requires-Dist: tox; extra == "dev"
Requires-Dist: pre-commit; extra == "dev"
Requires-Dist: ruff; extra == "dev"
Requires-Dist: towncrier; extra == "dev"
Dynamic: license-file
